{
  "KDHartreeFock_V1_0": 57.6272346534,
  "KDHartreeFock_V1_asymm": 14.515742515,
  "KDHartreeFock_V1_A": 0.0228241129,
  "KDHartreeFock_V2_0_n": 0.0053849309,
  "KDHartreeFock_V2_A_n": -2.2877e-06,
  "KDHartreeFock_V3_0_n": 8.939e-07,
  "KDHartreeFock_V3_A_n": -1.8109e-06,
  "KDHartreeFock_V2_0_p": 0.0055472691,
  "KDHartreeFock_V2_A_p": 6.2351e-06,
  "KDHartreeFock_V3_0_p": 4.4288e-06,
  "KDHartreeFock_V3_A_p": -3.0644e-06,
  "KDHartreeFock_V4_0": 5.517e-07,
  "KDHartreeFock_r_0": 1.2904427072,
  "KDHartreeFock_r_A": 0.3919351228,
  "KDHartreeFock_a_0": 0.6488601745,
  "KDHartreeFock_a_A": -9.41877e-05,
  "KDCoulomb_r_C_0": 0.9761540355,
  "KDCoulomb_r_C_A": 2.2944254431,
  "KDCoulomb_r_C_A2": 45.8029680605,
  "KDRealSpinOrbit_V1_0": 7.8525510752,
  "KDRealSpinOrbit_V1_A": -0.0117591715,
  "KDRealSpinOrbit_V2_0": 0.0076175005,
  "KDRealSpinOrbit_r_0": 1.3166223017,
  "KDRealSpinOrbit_r_A": 1.092119937,
  "KDRealSpinOrbit_a_0": 0.6003611112,
  "KDImagSpinOrbit_W1_0": -0.816097103,
  "KDImagSpinOrbit_W2_0": 123.8997588094,
  "KDImagVolume_W1_0_n": 19.5636354544,
  "KDImagVolume_W1_A_n": -0.0332525556,
  "KDImagVolume_W1_0_p": 21.3851940058,
  "KDImagVolume_W1_A_p": 0.0033652612,
  "KDImagVolume_W2_0": 112.097637901,
  "KDImagVolume_W2_A": -0.3503124461,
  "KDImagSurface_D1_0": 7.260523608,
  "KDImagSurface_D1_asymm": 17.3605862348,
  "KDImagSurface_D2_0": 0.0084151427,
  "KDImagSurface_D2_A": 0.004468782,
  "KDImagSurface_D2_A2": -2.907418215,
  "KDImagSurface_D2_A3": 346.7291929847,
  "KDImagSurface_D3_0": 6.9661286173,
  "KDImagSurface_r_0": 1.489118376,
  "KDImagSurface_r_A": 0.0520137682,
  "KDImagSurface_a_0_n": 0.5497819864,
  "KDImagSurface_a_A_n": -0.0003852459,
  "KDImagSurface_a_0_p": 0.5030756733,
  "KDImagSurface_a_A_p": 0.0007864935
}