{
  "KDHartreeFock_V1_0": 57.2511785532,
  "KDHartreeFock_V1_asymm": 19.7798100891,
  "KDHartreeFock_V1_A": 0.0067529119,
  "KDHartreeFock_V2_0_n": 0.006328524,
  "KDHartreeFock_V2_A_n": -1.459e-07,
  "KDHartreeFock_V3_0_n": 1.02665e-05,
  "KDHartreeFock_V3_A_n": 2.2111e-06,
  "KDHartreeFock_V2_0_p": 0.0067076936,
  "KDHartreeFock_V2_A_p": 9.9933e-06,
  "KDHartreeFock_V3_0_p": 8.4853e-06,
  "KDHartreeFock_V3_A_p": 7.765e-07,
  "KDHartreeFock_V4_0": 1.7663e-06,
  "KDHartreeFock_r_0": 1.1550954755,
  "KDHartreeFock_r_A": -0.1518248569,
  "KDHartreeFock_a_0": 0.6113833951,
  "KDHartreeFock_a_A": -0.000962704,
  "KDCoulomb_r_C_0": 1.2040463371,
  "KDCoulomb_r_C_A": 0.8115083326,
  "KDCoulomb_r_C_A2": 3.2909814876,
  "KDRealSpinOrbit_V1_0": 5.646053769,
  "KDRealSpinOrbit_V1_A": 0.0018856215,
  "KDRealSpinOrbit_V2_0": 0.0046286451,
  "KDRealSpinOrbit_r_0": 1.2487575687,
  "KDRealSpinOrbit_r_A": 1.005060387,
  "KDRealSpinOrbit_a_0": 0.6304250831,
  "KDImagSpinOrbit_W1_0": -4.6862154137,
  "KDImagSpinOrbit_W2_0": 235.5513002671,
  "KDImagVolume_W1_0_n": 19.4449393173,
  "KDImagVolume_W1_A_n": -0.0044880225,
  "KDImagVolume_W1_0_p": 19.0690798767,
  "KDImagVolume_W1_A_p": 0.0247227019,
  "KDImagVolume_W2_0": 99.7718912024,
  "KDImagVolume_W2_A": 0.0047377045,
  "KDImagSurface_D1_0": 26.9335441061,
  "KDImagSurface_D1_asymm": 16.901010016,
  "KDImagSurface_D2_0": 0.0535581479,
  "KDImagSurface_D2_A": -0.0180274187,
  "KDImagSurface_D2_A2": 8.5478687716,
  "KDImagSurface_D2_A3": 15.185729317,
  "KDImagSurface_D3_0": 18.2701796333,
  "KDImagSurface_r_0": 1.2649168619,
  "KDImagSurface_r_A": 0.0008166606,
  "KDImagSurface_a_0_n": 0.463726123,
  "KDImagSurface_a_A_n": -0.000543186,
  "KDImagSurface_a_0_p": 0.4284890879,
  "KDImagSurface_a_A_p": 0.0015230807
}