{
  "KDHartreeFock_V1_0": 58.7695316057,
  "KDHartreeFock_V1_asymm": 12.9699273685,
  "KDHartreeFock_V1_A": 0.025627784,
  "KDHartreeFock_V2_0_n": 0.0049427576,
  "KDHartreeFock_V2_A_n": 7.97e-08,
  "KDHartreeFock_V3_0_n": -1.754e-07,
  "KDHartreeFock_V3_A_n": -3.65e-08,
  "KDHartreeFock_V2_0_p": 0.0040965475,
  "KDHartreeFock_V2_A_p": 9.2961e-06,
  "KDHartreeFock_V3_0_p": -1.7732e-06,
  "KDHartreeFock_V3_A_p": -1.0821e-06,
  "KDHartreeFock_V4_0": -1.9893e-06,
  "KDHartreeFock_r_0": 1.3175995083,
  "KDHartreeFock_r_A": 0.6327522095,
  "KDHartreeFock_a_0": 0.7027078093,
  "KDHartreeFock_a_A": 6.45777e-05,
  "KDCoulomb_r_C_0": 1.2848946079,
  "KDCoulomb_r_C_A": 1.6885766657,
  "KDCoulomb_r_C_A2": 15.6452994775,
  "KDRealSpinOrbit_V1_0": 5.1494626887,
  "KDRealSpinOrbit_V1_A": 0.0116474918,
  "KDRealSpinOrbit_V2_0": 0.009573618,
  "KDRealSpinOrbit_r_0": 1.1926546604,
  "KDRealSpinOrbit_r_A": 0.5415406507,
  "KDRealSpinOrbit_a_0": 0.6578296012,
  "KDImagSpinOrbit_W1_0": -6.3157365462,
  "KDImagSpinOrbit_W2_0": 254.4956450607,
  "KDImagVolume_W1_0_n": 21.5149105724,
  "KDImagVolume_W1_A_n": 0.0264972614,
  "KDImagVolume_W1_0_p": 13.7844913676,
  "KDImagVolume_W1_A_p": 0.1137927195,
  "KDImagVolume_W2_0": 91.5922327572,
  "KDImagVolume_W2_A": 0.3404724763,
  "KDImagSurface_D1_0": 21.4260713199,
  "KDImagSurface_D1_asymm": 16.6052766969,
  "KDImagSurface_D2_0": -0.0013866079,
  "KDImagSurface_D2_A": 0.0303800287,
  "KDImagSurface_D2_A2": 24.0484113348,
  "KDImagSurface_D2_A3": 234.9926443305,
  "KDImagSurface_D3_0": 16.9197290457,
  "KDImagSurface_r_0": 1.3383085367,
  "KDImagSurface_r_A": 0.0155534504,
  "KDImagSurface_a_0_n": 0.5263575909,
  "KDImagSurface_a_A_n": -0.0003004627,
  "KDImagSurface_a_0_p": 0.4830658435,
  "KDImagSurface_a_A_p": 0.0013185746
}