{
  "CH89RealCentral_V_0": 55.4134546525,
  "CH89RealCentral_V_t": 12.0809661011,
  "CH89RealCentral_V_e": -0.3055906728,
  "CH89RealCentral_r_o": 1.1849186542,
  "CH89RealCentral_r_o_0": -0.1848369941,
  "CH89RealCentral_a_0": 0.7888811894,
  "CH89Coulomb_r_c": 1.4828886892,
  "CH89Coulomb_r_c_0": 0.2321695975,
  "CH89SpinOrbit_V_so": 5.6491264822,
  "CH89SpinOrbit_r_so": 1.2780163698,
  "CH89SpinOrbit_r_so_0": -0.7214282805,
  "CH89SpinOrbit_a_so": 0.603096548,
  "CH89ImagCentral_W_v0": 5.629722567,
  "CH89ImagCentral_W_ve0": 21.6792343545,
  "CH89ImagCentral_W_vew": 12.023438553,
  "CH89ImagCentral_W_s0": 13.0372179122,
  "CH89ImagCentral_W_st": 34.9821494826,
  "CH89ImagCentral_W_se0": 15.2170084926,
  "CH89ImagCentral_W_sew": 29.0969996271,
  "CH89ImagCentral_r_w": 1.3970513761,
  "CH89ImagCentral_r_w0": -0.580627839,
  "CH89ImagCentral_a_w": 0.695526235
}