{
  "CH89RealCentral_V_0": 55.3907306005,
  "CH89RealCentral_V_t": 12.0090078626,
  "CH89RealCentral_V_e": -0.3932614183,
  "CH89RealCentral_r_o": 1.1952917003,
  "CH89RealCentral_r_o_0": -0.1204189376,
  "CH89RealCentral_a_0": 0.6583553283,
  "CH89Coulomb_r_c": 1.1336121818,
  "CH89Coulomb_r_c_0": 0.2613307633,
  "CH89SpinOrbit_V_so": 5.4557320276,
  "CH89SpinOrbit_r_so": 1.2419725357,
  "CH89SpinOrbit_r_so_0": -1.1433819855,
  "CH89SpinOrbit_a_so": 0.6639360749,
  "CH89ImagCentral_W_v0": 13.6518898994,
  "CH89ImagCentral_W_ve0": 16.4128972918,
  "CH89ImagCentral_W_vew": 19.440423944,
  "CH89ImagCentral_W_s0": 3.2287463837,
  "CH89ImagCentral_W_st": 26.1075846815,
  "CH89ImagCentral_W_se0": 29.7481445782,
  "CH89ImagCentral_W_sew": 35.2982595909,
  "CH89ImagCentral_r_w": 1.3579362893,
  "CH89ImagCentral_r_w0": -0.1447052056,
  "CH89ImagCentral_a_w": 0.7028426274
}