[
  {
    "WLHReal_V0_p": 54.6254312661,
    "WLHReal_V1_p": 0.3343531739,
    "WLHReal_V2_p": -0.0006523923,
    "WLHReal_V3_p": 4.2465e-06,
    "WLHReal_V4_p": 9.936082353,
    "WLHReal_V5_p": 0.1543992995,
    "WLHReal_V6_p": 0.0005565185,
    "WLHReal_r0_p": 1.3721198347,
    "WLHReal_r1_p": 0.3722484574,
    "WLHReal_r2_p": 0.0011116401,
    "WLHReal_r3_p": 1.11005e-05,
    "WLHReal_a0_p": 0.8246675158,
    "WLHReal_a1_p": 0.0002175223,
    "WLHReal_a2_p": 9.0387e-06,
    "WLHReal_a3_p": 0.0443624224,
    "WLHReal_a4_p": 0.6529406279,
    "WLHReal_V0_n": 47.5314667729,
    "WLHReal_V1_n": 0.2577476886,
    "WLHReal_V2_n": -0.0015002667,
    "WLHReal_V3_n": 6.4549e-06,
    "WLHReal_V4_n": 20.2093128151,
    "WLHReal_V5_n": 0.3578778545,
    "WLHReal_V6_n": 0.0022051495,
    "WLHReal_r0_n": 1.374118821,
    "WLHReal_r1_n": 0.2465955678,
    "WLHReal_r2_n": 0.0017544704,
    "WLHReal_r3_n": 2.4421e-05,
    "WLHReal_a0_n": 0.8003822761,
    "WLHReal_a1_n": 0.0020108103,
    "WLHReal_a2_n": 3.06485e-05,
    "WLHReal_a3_n": 0.4626538054,
    "WLHReal_a4_n": 1.3598356275,
    "WLHImagVolume_W0_p": 6.3883598207,
    "WLHImagVolume_W1_p": 0.3376351179,
    "WLHImagVolume_W2_p": 0.0007521533,
    "WLHImagVolume_W3_p": 13.6871688468,
    "WLHImagVolume_W4_p": 0.1138918368,
    "WLHImagVolume_r0_p": 0.5633351476,
    "WLHImagVolume_r1_p": 60.0006782865,
    "WLHImagVolume_r2_p": 0.7635701191,
    "WLHImagVolume_r3_p": 69.9958143586,
    "WLHImagVolume_r4_p": 0.5380255536,
    "WLHImagVolume_r5_p": 9.226e-07,
    "WLHImagVolume_a0_p": 0.6213887484,
    "WLHImagVolume_a1_p": 0.2756402681,
    "WLHImagVolume_a2_p": 15.2878398728,
    "WLHImagVolume_a3_p": 0.4765872405,
    "WLHImagVolume_a4_p": 0.0033822645,
    "WLHImagVolume_W0_n": 4.2080044156,
    "WLHImagVolume_W1_n": 0.2499194473,
    "WLHImagVolume_W2_n": 0.0006425501,
    "WLHImagVolume_W3_n": 10.2816976799,
    "WLHImagVolume_W4_n": -0.0253559337,
    "WLHImagVolume_r0_n": 0.6338849796,
    "WLHImagVolume_r1_n": 94.5544743964,
    "WLHImagVolume_r2_n": 0.7376142852,
    "WLHImagVolume_r3_n": 114.2171465776,
    "WLHImagVolume_r4_n": 0.9301982575,
    "WLHImagVolume_r5_n": 6.3793e-06,
    "WLHImagVolume_a0_n": 0.3285245615,
    "WLHImagVolume_a1_n": 0.5030836704,
    "WLHImagVolume_a2_n": 2.3935668306,
    "WLHImagVolume_a3_n": 0.0331101547,
    "WLHImagVolume_a4_n": 3.1105e-05,
    "WLHImagSurface_W0_p": 0.6852283846,
    "WLHImagSurface_W1_p": 0.0308670457,
    "WLHImagSurface_W2_p": 0.290490561,
    "WLHImagSurface_W3_p": 0.1212179468,
    "WLHImagSurface_r0_p": 0.8659516152,
    "WLHImagSurface_r1_p": 0.3470516745,
    "WLHImagSurface_r2_p": -9.07522e-05,
    "WLHImagSurface_a0_p": 0.7636207224,
    "WLHImagSurface_W0_n": 1.4654149818,
    "WLHImagSurface_W1_n": 0.0637009177,
    "WLHImagSurface_W2_n": 1.9064791871,
    "WLHImagSurface_W3_n": 0.2198623538,
    "WLHImagSurface_r0_n": 1.3168429029,
    "WLHImagSurface_r1_n": 1.7231228382,
    "WLHImagSurface_r2_n": 0.0008400047,
    "WLHImagSurface_a0_n": 0.9091653293,
    "WLHRealSpinOrbit_V0_p": 9.131101631,
    "WLHRealSpinOrbit_V1_p": 0.0086468153,
    "WLHRealSpinOrbit_r0_p": 1.3284384655,
    "WLHRealSpinOrbit_r1_p": 0.9665160707,
    "WLHRealSpinOrbit_a0_p": 0.8471104533,
    "WLHRealSpinOrbit_a1_p": 0.0003156368,
    "WLHRealSpinOrbit_V0_n": 9.1401970102,
    "WLHRealSpinOrbit_V1_n": 0.0091650554,
    "WLHRealSpinOrbit_r0_n": 1.3819370026,
    "WLHRealSpinOrbit_r1_n": 1.0440191493,
    "WLHRealSpinOrbit_a0_n": 0.8920385043,
    "WLHRealSpinOrbit_a1_n": 0.0003291219
  }
]