[
  {
    "WLHReal_V0_p": 57.3830817995,
    "WLHReal_V1_p": 0.2980326959,
    "WLHReal_V2_p": 0.0007206452,
    "WLHReal_V3_p": -1.4193e-06,
    "WLHReal_V4_p": 16.1041142578,
    "WLHReal_V5_p": 0.1223737408,
    "WLHReal_V6_p": 5.38078e-05,
    "WLHReal_r0_p": 1.1950552875,
    "WLHReal_r1_p": 0.2244191947,
    "WLHReal_r2_p": 0.0006186407,
    "WLHReal_r3_p": 2.2317e-06,
    "WLHReal_a0_p": 0.7371994632,
    "WLHReal_a1_p": 0.0002143381,
    "WLHReal_a2_p": -3.901e-07,
    "WLHReal_a3_p": 0.112315138,
    "WLHReal_a4_p": 0.5777875061,
    "WLHReal_V0_n": 46.7546204117,
    "WLHReal_V1_n": 0.2662527407,
    "WLHReal_V2_n": -0.0013384015,
    "WLHReal_V3_n": 6.8163e-06,
    "WLHReal_V4_n": 19.6220078001,
    "WLHReal_V5_n": 0.3504142898,
    "WLHReal_V6_n": 0.0020040434,
    "WLHReal_r0_n": 1.3978548972,
    "WLHReal_r1_n": 0.3159200283,
    "WLHReal_r2_n": 0.0015708847,
    "WLHReal_r3_n": 2.01168e-05,
    "WLHReal_a0_n": 0.790939698,
    "WLHReal_a1_n": 0.0018728152,
    "WLHReal_a2_n": 2.72549e-05,
    "WLHReal_a3_n": 0.3947832586,
    "WLHReal_a4_n": 1.2081511395,
    "WLHImagVolume_W0_p": 2.7406449054,
    "WLHImagVolume_W1_p": 0.2089451811,
    "WLHImagVolume_W2_p": 0.0001264563,
    "WLHImagVolume_W3_p": 13.4221930012,
    "WLHImagVolume_W4_p": 0.0583743023,
    "WLHImagVolume_r0_p": 0.7044506123,
    "WLHImagVolume_r1_p": 32.2183663426,
    "WLHImagVolume_r2_p": 0.4458927781,
    "WLHImagVolume_r3_p": 46.7937902881,
    "WLHImagVolume_r4_p": 0.8340364482,
    "WLHImagVolume_r5_p": 3.0205e-06,
    "WLHImagVolume_a0_p": 0.5103112691,
    "WLHImagVolume_a1_p": 0.2449613384,
    "WLHImagVolume_a2_p": 11.0141776593,
    "WLHImagVolume_a3_p": 0.3934149728,
    "WLHImagVolume_a4_p": 0.0018404826,
    "WLHImagVolume_W0_n": 3.5570077269,
    "WLHImagVolume_W1_n": 0.2436816136,
    "WLHImagVolume_W2_n": 0.0007844414,
    "WLHImagVolume_W3_n": 8.7970383241,
    "WLHImagVolume_W4_n": -0.020911501,
    "WLHImagVolume_r0_n": 0.5118708026,
    "WLHImagVolume_r1_n": 117.4157139665,
    "WLHImagVolume_r2_n": 0.877944604,
    "WLHImagVolume_r3_n": 124.0793842569,
    "WLHImagVolume_r4_n": 0.7763767378,
    "WLHImagVolume_r5_n": 5.1776e-06,
    "WLHImagVolume_a0_n": 0.2990353955,
    "WLHImagVolume_a1_n": 0.5437540712,
    "WLHImagVolume_a2_n": 3.5353911708,
    "WLHImagVolume_a3_n": 0.05529395,
    "WLHImagVolume_a4_n": 8.96583e-05,
    "WLHImagSurface_W0_p": 1.0064180669,
    "WLHImagSurface_W1_p": 0.0275710537,
    "WLHImagSurface_W2_p": 0.9005604187,
    "WLHImagSurface_W3_p": 0.0818368042,
    "WLHImagSurface_r0_p": 1.0453024644,
    "WLHImagSurface_r1_p": 0.8661450866,
    "WLHImagSurface_r2_p": 0.0093268945,
    "WLHImagSurface_a0_p": 0.7107960361,
    "WLHImagSurface_W0_n": 1.6627333872,
    "WLHImagSurface_W1_n": 0.0709982323,
    "WLHImagSurface_W2_n": 2.883179118,
    "WLHImagSurface_W3_n": 0.2562445979,
    "WLHImagSurface_r0_n": 1.359627918,
    "WLHImagSurface_r1_n": 1.784159514,
    "WLHImagSurface_r2_n": 0.0011648199,
    "WLHImagSurface_a0_n": 0.9075489565,
    "WLHRealSpinOrbit_V0_p": 10.7236505978,
    "WLHRealSpinOrbit_V1_p": 0.0086363537,
    "WLHRealSpinOrbit_r0_p": 1.1744199632,
    "WLHRealSpinOrbit_r1_p": 0.7210373988,
    "WLHRealSpinOrbit_a0_p": 0.7332638329,
    "WLHRealSpinOrbit_a1_p": 0.0003439842,
    "WLHRealSpinOrbit_V0_n": 8.5901844957,
    "WLHRealSpinOrbit_V1_n": 0.0085947339,
    "WLHRealSpinOrbit_r0_n": 1.3902944741,
    "WLHRealSpinOrbit_r1_n": 1.0368739863,
    "WLHRealSpinOrbit_a0_n": 0.8858432391,
    "WLHRealSpinOrbit_a1_n": 0.0003589009
  }
]