{
  "WLHReal_V0_p": 49.6200170554,
  "WLHReal_V1_p": 0.3082447798,
  "WLHReal_V2_p": -0.000550468,
  "WLHReal_V3_p": 3.7073e-06,
  "WLHReal_V4_p": 10.6891533649,
  "WLHReal_V5_p": 0.1149675803,
  "WLHReal_V6_p": 0.0004063725,
  "WLHReal_r0_p": 1.3588786725,
  "WLHReal_r1_p": 0.2598746967,
  "WLHReal_r2_p": 0.0009988291,
  "WLHReal_r3_p": 1.04995e-05,
  "WLHReal_a0_p": 0.7963228014,
  "WLHReal_a1_p": -0.0001100807,
  "WLHReal_a2_p": 9.9366e-06,
  "WLHReal_a3_p": -0.0016891689,
  "WLHReal_a4_p": 0.5561419701,
  "WLHReal_V0_n": 51.3112893513,
  "WLHReal_V1_n": 0.280070191,
  "WLHReal_V2_n": -0.0001036881,
  "WLHReal_V3_n": 2.5959e-06,
  "WLHReal_V4_n": 20.8806726153,
  "WLHReal_V5_n": 0.2725906743,
  "WLHReal_V6_n": 0.0008567608,
  "WLHReal_r0_n": 1.3173731317,
  "WLHReal_r1_n": 0.3655588917,
  "WLHReal_r2_n": 0.0007105042,
  "WLHReal_r3_n": 5.2004e-06,
  "WLHReal_a0_n": 0.7299541622,
  "WLHReal_a1_n": 0.0006949984,
  "WLHReal_a2_n": 6.825e-06,
  "WLHReal_a3_n": 0.2265200514,
  "WLHReal_a4_n": 0.735041445,
  "WLHImagVolume_W0_p": 4.767475958,
  "WLHImagVolume_W1_p": 0.1875727899,
  "WLHImagVolume_W2_p": 0.0004383682,
  "WLHImagVolume_W3_p": 9.492831489,
  "WLHImagVolume_W4_p": 0.0697903445,
  "WLHImagVolume_r0_p": 0.6006642652,
  "WLHImagVolume_r1_p": 67.3479710022,
  "WLHImagVolume_r2_p": 0.7415430707,
  "WLHImagVolume_r3_p": 79.6977847736,
  "WLHImagVolume_r4_p": 0.4744169642,
  "WLHImagVolume_r5_p": 1.0317e-06,
  "WLHImagVolume_a0_p": 0.5545117714,
  "WLHImagVolume_a1_p": 0.3226080716,
  "WLHImagVolume_a2_p": 19.9152161738,
  "WLHImagVolume_a3_p": 0.3811881921,
  "WLHImagVolume_a4_p": 0.0020385748,
  "WLHImagVolume_W0_n": 2.0269650467,
  "WLHImagVolume_W1_n": 0.2167997308,
  "WLHImagVolume_W2_n": 0.0005039549,
  "WLHImagVolume_W3_n": 6.8720105503,
  "WLHImagVolume_W4_n": 0.0167136715,
  "WLHImagVolume_r0_n": 0.4649813707,
  "WLHImagVolume_r1_n": 98.5299191089,
  "WLHImagVolume_r2_n": 0.8376115965,
  "WLHImagVolume_r3_n": 92.6607276032,
  "WLHImagVolume_r4_n": 0.7955991269,
  "WLHImagVolume_r5_n": 2.4545e-06,
  "WLHImagVolume_a0_n": 0.2083823133,
  "WLHImagVolume_a1_n": 0.6248271058,
  "WLHImagVolume_a2_n": 8.6595156334,
  "WLHImagVolume_a3_n": 0.0867986178,
  "WLHImagVolume_a4_n": 0.0007305462,
  "WLHImagSurface_W0_p": 0.9265821178,
  "WLHImagSurface_W1_p": 0.0410276427,
  "WLHImagSurface_W2_p": 0.4715646491,
  "WLHImagSurface_W3_p": 0.1324790057,
  "WLHImagSurface_r0_p": 0.9848447462,
  "WLHImagSurface_r1_p": 0.1047765499,
  "WLHImagSurface_r2_p": 0.0009549179,
  "WLHImagSurface_a0_p": 0.938264944,
  "WLHImagSurface_W0_n": 1.6076026671,
  "WLHImagSurface_W1_n": 0.0380177624,
  "WLHImagSurface_W2_n": 2.8556627928,
  "WLHImagSurface_W3_n": 0.1537826656,
  "WLHImagSurface_r0_n": 1.323510054,
  "WLHImagSurface_r1_n": 1.474214382,
  "WLHImagSurface_r2_n": 0.0033112743,
  "WLHImagSurface_a0_n": 0.8503810365,
  "WLHRealSpinOrbit_V0_p": 8.7552760577,
  "WLHRealSpinOrbit_V1_p": 0.0082511722,
  "WLHRealSpinOrbit_r0_p": 1.3380580708,
  "WLHRealSpinOrbit_r1_p": 0.958804168,
  "WLHRealSpinOrbit_a0_p": 0.8443980775,
  "WLHRealSpinOrbit_a1_p": 0.0003574267,
  "WLHRealSpinOrbit_V0_n": 9.1684998156,
  "WLHRealSpinOrbit_V1_n": 0.0080298312,
  "WLHRealSpinOrbit_r0_n": 1.2858842659,
  "WLHRealSpinOrbit_r1_n": 0.8595111061,
  "WLHRealSpinOrbit_a0_n": 0.7981791186,
  "WLHRealSpinOrbit_a1_n": 0.0003872588
}