[
  {
    "WLHReal_V0_p": 49.9278415848,
    "WLHReal_V1_p": 0.2746589557,
    "WLHReal_V2_p": -0.0004057489,
    "WLHReal_V3_p": 2.5038e-06,
    "WLHReal_V4_p": 12.8224992116,
    "WLHReal_V5_p": 0.1096083309,
    "WLHReal_V6_p": 0.0003652245,
    "WLHReal_r0_p": 1.314412398,
    "WLHReal_r1_p": 0.206057536,
    "WLHReal_r2_p": 0.0008980994,
    "WLHReal_r3_p": 9.9539e-06,
    "WLHReal_a0_p": 0.7761545937,
    "WLHReal_a1_p": -8.3743e-05,
    "WLHReal_a2_p": 8.9959e-06,
    "WLHReal_a3_p": -0.0123870676,
    "WLHReal_a4_p": 0.5056515187,
    "WLHReal_V0_n": 50.3506858583,
    "WLHReal_V1_n": 0.2892789601,
    "WLHReal_V2_n": -0.0011557121,
    "WLHReal_V3_n": 5.7139e-06,
    "WLHReal_V4_n": 19.7390546786,
    "WLHReal_V5_n": 0.3479384138,
    "WLHReal_V6_n": 0.0019112001,
    "WLHReal_r0_n": 1.3635462255,
    "WLHReal_r1_n": 0.3117781854,
    "WLHReal_r2_n": 0.0014986033,
    "WLHReal_r3_n": 1.90791e-05,
    "WLHReal_a0_n": 0.7871822246,
    "WLHReal_a1_n": 0.0016366104,
    "WLHReal_a2_n": 2.43143e-05,
    "WLHReal_a3_n": 0.3700170933,
    "WLHReal_a4_n": 1.1785614253,
    "WLHImagVolume_W0_p": 4.1247366437,
    "WLHImagVolume_W1_p": 0.146426493,
    "WLHImagVolume_W2_p": 0.0001008951,
    "WLHImagVolume_W3_p": 8.4531936084,
    "WLHImagVolume_W4_p": 0.0592758972,
    "WLHImagVolume_r0_p": 0.7871235615,
    "WLHImagVolume_r1_p": 38.722312443,
    "WLHImagVolume_r2_p": 0.5083735495,
    "WLHImagVolume_r3_p": 56.4371422874,
    "WLHImagVolume_r4_p": 0.6846441336,
    "WLHImagVolume_r5_p": 1.2335e-06,
    "WLHImagVolume_a0_p": 0.5613940901,
    "WLHImagVolume_a1_p": 0.2705114297,
    "WLHImagVolume_a2_p": 15.0676406171,
    "WLHImagVolume_a3_p": 0.3998738991,
    "WLHImagVolume_a4_p": 0.0022571218,
    "WLHImagVolume_W0_n": 4.2092818421,
    "WLHImagVolume_W1_n": 0.3042318657,
    "WLHImagVolume_W2_n": 0.0008419072,
    "WLHImagVolume_W3_n": 10.5607568816,
    "WLHImagVolume_W4_n": 0.0149838082,
    "WLHImagVolume_r0_n": 0.5692421087,
    "WLHImagVolume_r1_n": 96.4507457357,
    "WLHImagVolume_r2_n": 0.7905953273,
    "WLHImagVolume_r3_n": 112.5369551894,
    "WLHImagVolume_r4_n": 0.8812371051,
    "WLHImagVolume_r5_n": 5.1318e-06,
    "WLHImagVolume_a0_n": 0.3097362438,
    "WLHImagVolume_a1_n": 0.5279572946,
    "WLHImagVolume_a2_n": 2.223837935,
    "WLHImagVolume_a3_n": 0.0190437454,
    "WLHImagVolume_a4_n": 9.82742e-05,
    "WLHImagSurface_W0_p": 0.7551556453,
    "WLHImagSurface_W1_p": 0.0174299523,
    "WLHImagSurface_W2_p": 0.2382815191,
    "WLHImagSurface_W3_p": 0.0415270987,
    "WLHImagSurface_r0_p": 0.9003412081,
    "WLHImagSurface_r1_p": 0.0538065151,
    "WLHImagSurface_r2_p": 0.0023028313,
    "WLHImagSurface_a0_p": 0.8144208054,
    "WLHImagSurface_W0_n": 1.9550078781,
    "WLHImagSurface_W1_n": 0.0735329904,
    "WLHImagSurface_W2_n": 3.0063275639,
    "WLHImagSurface_W3_n": 0.2459141834,
    "WLHImagSurface_r0_n": 1.3206631091,
    "WLHImagSurface_r1_n": 1.7775582218,
    "WLHImagSurface_r2_n": 0.0017028057,
    "WLHImagSurface_a0_n": 0.8895386153,
    "WLHRealSpinOrbit_V0_p": 9.4176761147,
    "WLHRealSpinOrbit_V1_p": 0.0085982751,
    "WLHRealSpinOrbit_r0_p": 1.3086743901,
    "WLHRealSpinOrbit_r1_p": 0.911526606,
    "WLHRealSpinOrbit_a0_p": 0.8266713458,
    "WLHRealSpinOrbit_a1_p": 0.0003647848,
    "WLHRealSpinOrbit_V0_n": 9.0976738068,
    "WLHRealSpinOrbit_V1_n": 0.0088871012,
    "WLHRealSpinOrbit_r0_n": 1.3571212289,
    "WLHRealSpinOrbit_r1_n": 1.008034914,
    "WLHRealSpinOrbit_a0_n": 0.8708245943,
    "WLHRealSpinOrbit_a1_n": 0.0003235443
  }
]