[
  {
    "WLHReal_V0_p": 55.8164400044,
    "WLHReal_V1_p": 0.3325788158,
    "WLHReal_V2_p": 0.0002965597,
    "WLHReal_V3_p": 1.0936e-06,
    "WLHReal_V4_p": 12.8924503467,
    "WLHReal_V5_p": 0.1312273207,
    "WLHReal_V6_p": 0.0001893287,
    "WLHReal_r0_p": 1.2762030969,
    "WLHReal_r1_p": 0.3016270756,
    "WLHReal_r2_p": 0.0007808763,
    "WLHReal_r3_p": 4.4725e-06,
    "WLHReal_a0_p": 0.7715553501,
    "WLHReal_a1_p": 0.0001545288,
    "WLHReal_a2_p": 3.5301e-06,
    "WLHReal_a3_p": 0.1005052284,
    "WLHReal_a4_p": 0.6215794561,
    "WLHReal_V0_n": 51.7670414378,
    "WLHReal_V1_n": 0.2725756745,
    "WLHReal_V2_n": -0.0008063934,
    "WLHReal_V3_n": 4.4007e-06,
    "WLHReal_V4_n": 20.3737945731,
    "WLHReal_V5_n": 0.328310238,
    "WLHReal_V6_n": 0.0015136507,
    "WLHReal_r0_n": 1.3557676675,
    "WLHReal_r1_n": 0.3943489587,
    "WLHReal_r2_n": 0.0011133679,
    "WLHReal_r3_n": 1.16043e-05,
    "WLHReal_a0_n": 0.7664456345,
    "WLHReal_a1_n": 0.0011010193,
    "WLHReal_a2_n": 1.59556e-05,
    "WLHReal_a3_n": 0.2710594939,
    "WLHReal_a4_n": 0.9145051151,
    "WLHImagVolume_W0_p": 3.9248082055,
    "WLHImagVolume_W1_p": 0.2559250008,
    "WLHImagVolume_W2_p": 0.0005369984,
    "WLHImagVolume_W3_p": 13.7982046659,
    "WLHImagVolume_W4_p": 0.0750478343,
    "WLHImagVolume_r0_p": 0.4990536759,
    "WLHImagVolume_r1_p": 65.8194015497,
    "WLHImagVolume_r2_p": 0.7363320521,
    "WLHImagVolume_r3_p": 74.1659130162,
    "WLHImagVolume_r4_p": 0.5571522266,
    "WLHImagVolume_r5_p": 1.6895e-06,
    "WLHImagVolume_a0_p": 0.5201005119,
    "WLHImagVolume_a1_p": 0.3064795478,
    "WLHImagVolume_a2_p": 17.0509009031,
    "WLHImagVolume_a3_p": 0.3824307455,
    "WLHImagVolume_a4_p": 0.0018092042,
    "WLHImagVolume_W0_n": 3.4984056478,
    "WLHImagVolume_W1_n": 0.3029915093,
    "WLHImagVolume_W2_n": 0.000699487,
    "WLHImagVolume_W3_n": 9.6313867692,
    "WLHImagVolume_W4_n": 0.0253656306,
    "WLHImagVolume_r0_n": 0.5631058008,
    "WLHImagVolume_r1_n": 82.8612457963,
    "WLHImagVolume_r2_n": 0.7791892752,
    "WLHImagVolume_r3_n": 97.7360027599,
    "WLHImagVolume_r4_n": 0.961639483,
    "WLHImagVolume_r5_n": 5.4708e-06,
    "WLHImagVolume_a0_n": 0.2971781589,
    "WLHImagVolume_a1_n": 0.5578216896,
    "WLHImagVolume_a2_n": 4.5169455019,
    "WLHImagVolume_a3_n": 0.0564649875,
    "WLHImagVolume_a4_n": 0.0007811279,
    "WLHImagSurface_W0_p": 1.145386302,
    "WLHImagSurface_W1_p": 0.0540497511,
    "WLHImagSurface_W2_p": 1.1103656633,
    "WLHImagSurface_W3_p": 0.1872504299,
    "WLHImagSurface_r0_p": 1.0999233709,
    "WLHImagSurface_r1_p": 0.7755053208,
    "WLHImagSurface_r2_p": 0.0061850472,
    "WLHImagSurface_a0_p": 0.8546822186,
    "WLHImagSurface_W0_n": 1.7364670088,
    "WLHImagSurface_W1_n": 0.0564628705,
    "WLHImagSurface_W2_n": 2.9893446828,
    "WLHImagSurface_W3_n": 0.2066979081,
    "WLHImagSurface_r0_n": 1.2997523068,
    "WLHImagSurface_r1_n": 1.6438971598,
    "WLHImagSurface_r2_n": 0.0022580585,
    "WLHImagSurface_a0_n": 0.8732850835,
    "WLHRealSpinOrbit_V0_p": 9.6854682031,
    "WLHRealSpinOrbit_V1_p": 0.0082413443,
    "WLHRealSpinOrbit_r0_p": 1.2379546918,
    "WLHRealSpinOrbit_r1_p": 0.8177413842,
    "WLHRealSpinOrbit_a0_p": 0.7743984325,
    "WLHRealSpinOrbit_a1_p": 0.0003391466,
    "WLHRealSpinOrbit_V0_n": 9.2702562774,
    "WLHRealSpinOrbit_V1_n": 0.0086826248,
    "WLHRealSpinOrbit_r0_n": 1.3314284109,
    "WLHRealSpinOrbit_r1_n": 0.9478543845,
    "WLHRealSpinOrbit_a0_n": 0.8435912496,
    "WLHRealSpinOrbit_a1_n": 0.0003542668
  }
]