{
  "WLHReal_V0_p": 52.1638525128,
  "WLHReal_V1_p": 0.3175029367,
  "WLHReal_V2_p": -0.0009777829,
  "WLHReal_V3_p": 5.0734e-06,
  "WLHReal_V4_p": 9.6224251112,
  "WLHReal_V5_p": 0.1326607757,
  "WLHReal_V6_p": 0.0006150422,
  "WLHReal_r0_p": 1.3744664894,
  "WLHReal_r1_p": 0.2713571792,
  "WLHReal_r2_p": 0.0013361511,
  "WLHReal_r3_p": 1.51538e-05,
  "WLHReal_a0_p": 0.8277531911,
  "WLHReal_a1_p": 7.02355e-05,
  "WLHReal_a2_p": 1.31193e-05,
  "WLHReal_a3_p": -0.0011103057,
  "WLHReal_a4_p": 0.64973672,
  "WLHReal_V0_n": 52.7167578926,
  "WLHReal_V1_n": 0.2920778939,
  "WLHReal_V2_n": 0.0004302118,
  "WLHReal_V3_n": 4.598e-07,
  "WLHReal_V4_n": 21.7409258167,
  "WLHReal_V5_n": 0.2297813178,
  "WLHReal_V6_n": 0.0004380624,
  "WLHReal_r0_n": 1.2518451462,
  "WLHReal_r1_n": 0.2722003717,
  "WLHReal_r2_n": 0.0005167152,
  "WLHReal_r3_n": 2.1005e-06,
  "WLHReal_a0_n": 0.7057462537,
  "WLHReal_a1_n": 0.0004184289,
  "WLHReal_a2_n": 1.9712e-06,
  "WLHReal_a3_n": 0.2432179198,
  "WLHReal_a4_n": 0.716699141,
  "WLHImagVolume_W0_p": 6.5730344612,
  "WLHImagVolume_W1_p": 0.2922715384,
  "WLHImagVolume_W2_p": 0.0005675156,
  "WLHImagVolume_W3_p": 12.025037712,
  "WLHImagVolume_W4_p": 0.1052165295,
  "WLHImagVolume_r0_p": 0.7290793809,
  "WLHImagVolume_r1_p": 48.6002161498,
  "WLHImagVolume_r2_p": 0.6214578857,
  "WLHImagVolume_r3_p": 66.2739275531,
  "WLHImagVolume_r4_p": 0.6456146168,
  "WLHImagVolume_r5_p": 1.378e-06,
  "WLHImagVolume_a0_p": 0.6390414997,
  "WLHImagVolume_a1_p": 0.2577956682,
  "WLHImagVolume_a2_p": 14.4702171718,
  "WLHImagVolume_a3_p": 0.4832550899,
  "WLHImagVolume_a4_p": 0.0035628856,
  "WLHImagVolume_W0_n": 1.5602699417,
  "WLHImagVolume_W1_n": 0.167843067,
  "WLHImagVolume_W2_n": 0.0002626589,
  "WLHImagVolume_W3_n": 6.3540043527,
  "WLHImagVolume_W4_n": 0.0182462936,
  "WLHImagVolume_r0_n": 0.493390896,
  "WLHImagVolume_r1_n": 88.8901078004,
  "WLHImagVolume_r2_n": 0.7498491409,
  "WLHImagVolume_r3_n": 78.127935714,
  "WLHImagVolume_r4_n": 0.7927153737,
  "WLHImagVolume_r5_n": 1.5588e-06,
  "WLHImagVolume_a0_n": 0.1566671137,
  "WLHImagVolume_a1_n": 0.6435691215,
  "WLHImagVolume_a2_n": 10.668495549,
  "WLHImagVolume_a3_n": 0.0771461819,
  "WLHImagVolume_a4_n": 0.0005390322,
  "WLHImagSurface_W0_p": 0.3792000937,
  "WLHImagSurface_W1_p": -0.0020831731,
  "WLHImagSurface_W2_p": -0.7927477481,
  "WLHImagSurface_W3_p": -0.0145497484,
  "WLHImagSurface_r0_p": 0.7725767018,
  "WLHImagSurface_r1_p": -0.0303023694,
  "WLHImagSurface_r2_p": -0.002264762,
  "WLHImagSurface_a0_p": 0.7808559979,
  "WLHImagSurface_W0_n": 1.4894949773,
  "WLHImagSurface_W1_n": 0.0193016624,
  "WLHImagSurface_W2_n": 2.0379159342,
  "WLHImagSurface_W3_n": 0.0797439238,
  "WLHImagSurface_r0_n": 1.2998467456,
  "WLHImagSurface_r1_n": 1.2912167963,
  "WLHImagSurface_r2_n": 0.0041472811,
  "WLHImagSurface_a0_n": 0.8261172759,
  "WLHRealSpinOrbit_V0_p": 9.1497168076,
  "WLHRealSpinOrbit_V1_p": 0.0089630821,
  "WLHRealSpinOrbit_r0_p": 1.3546662821,
  "WLHRealSpinOrbit_r1_p": 1.0131511145,
  "WLHRealSpinOrbit_a0_p": 0.8721579912,
  "WLHRealSpinOrbit_a1_p": 0.0003085387,
  "WLHRealSpinOrbit_V0_n": 9.6744662281,
  "WLHRealSpinOrbit_V1_n": 0.0080228226,
  "WLHRealSpinOrbit_r0_n": 1.2288230359,
  "WLHRealSpinOrbit_r1_n": 0.7824805358,
  "WLHRealSpinOrbit_a0_n": 0.7598776265,
  "WLHRealSpinOrbit_a1_n": 0.0003768629
}