[
  {
    "WLHReal_V0_p": 52.6355203594,
    "WLHReal_V1_p": 0.2780364311,
    "WLHReal_V2_p": -0.0006136066,
    "WLHReal_V3_p": 3.4343e-06,
    "WLHReal_V4_p": 12.5936766677,
    "WLHReal_V5_p": 0.1290846195,
    "WLHReal_V6_p": 0.0005015268,
    "WLHReal_r0_p": 1.3168772132,
    "WLHReal_r1_p": 0.2351991496,
    "WLHReal_r2_p": 0.0010604118,
    "WLHReal_r3_p": 1.19456e-05,
    "WLHReal_a0_p": 0.7949787253,
    "WLHReal_a1_p": 0.0001053135,
    "WLHReal_a2_p": 8.8189e-06,
    "WLHReal_a3_p": -0.0022798927,
    "WLHReal_a4_p": 0.5635610188,
    "WLHReal_V0_n": 49.9161013204,
    "WLHReal_V1_n": 0.2667159255,
    "WLHReal_V2_n": -0.0014344881,
    "WLHReal_V3_n": 6.3141e-06,
    "WLHReal_V4_n": 19.9957122496,
    "WLHReal_V5_n": 0.3658741871,
    "WLHReal_V6_n": 0.0021336743,
    "WLHReal_r0_n": 1.3792304283,
    "WLHReal_r1_n": 0.3266710059,
    "WLHReal_r2_n": 0.0016121526,
    "WLHReal_r3_n": 2.11806e-05,
    "WLHReal_a0_n": 0.7987198015,
    "WLHReal_a1_n": 0.0017423507,
    "WLHReal_a2_n": 2.65016e-05,
    "WLHReal_a3_n": 0.3881827531,
    "WLHReal_a4_n": 1.2223918583,
    "WLHImagVolume_W0_p": 5.3193307005,
    "WLHImagVolume_W1_p": 0.2304095046,
    "WLHImagVolume_W2_p": 0.0001742908,
    "WLHImagVolume_W3_p": 10.5769910545,
    "WLHImagVolume_W4_p": 0.0868701113,
    "WLHImagVolume_r0_p": 0.880800176,
    "WLHImagVolume_r1_p": 20.6973700298,
    "WLHImagVolume_r2_p": 0.4042108003,
    "WLHImagVolume_r3_p": 41.3701637844,
    "WLHImagVolume_r4_p": 0.8318485514,
    "WLHImagVolume_r5_p": 1.991e-06,
    "WLHImagVolume_a0_p": 0.623750605,
    "WLHImagVolume_a1_p": 0.2133502224,
    "WLHImagVolume_a2_p": 9.9519524117,
    "WLHImagVolume_a3_p": 0.4815911263,
    "WLHImagVolume_a4_p": 0.0034419946,
    "WLHImagVolume_W0_n": 4.505862427,
    "WLHImagVolume_W1_n": 0.3142621459,
    "WLHImagVolume_W2_n": 0.0007755672,
    "WLHImagVolume_W3_n": 11.162761267,
    "WLHImagVolume_W4_n": 0.0055051446,
    "WLHImagVolume_r0_n": 0.6331139377,
    "WLHImagVolume_r1_n": 84.0467425349,
    "WLHImagVolume_r2_n": 0.7396573298,
    "WLHImagVolume_r3_n": 109.2819556445,
    "WLHImagVolume_r4_n": 0.9986221788,
    "WLHImagVolume_r5_n": 6.7408e-06,
    "WLHImagVolume_a0_n": 0.3470770174,
    "WLHImagVolume_a1_n": 0.5029592391,
    "WLHImagVolume_a2_n": 1.5817245057,
    "WLHImagVolume_a3_n": 0.027449103,
    "WLHImagVolume_a4_n": 0.0003537467,
    "WLHImagSurface_W0_p": 0.386339355,
    "WLHImagSurface_W1_p": -0.0109844684,
    "WLHImagSurface_W2_p": -0.4405828915,
    "WLHImagSurface_W3_p": -0.0501773117,
    "WLHImagSurface_r0_p": 0.7423601655,
    "WLHImagSurface_r1_p": 0.0457536299,
    "WLHImagSurface_r2_p": 0.000749114,
    "WLHImagSurface_a0_p": 0.6562761868,
    "WLHImagSurface_W0_n": 1.7132469691,
    "WLHImagSurface_W1_n": 0.0697716795,
    "WLHImagSurface_W2_n": 2.5791335148,
    "WLHImagSurface_W3_n": 0.2395600897,
    "WLHImagSurface_r0_n": 1.3012179495,
    "WLHImagSurface_r1_n": 1.767063786,
    "WLHImagSurface_r2_n": 0.0011522801,
    "WLHImagSurface_a0_n": 0.9001645822,
    "WLHRealSpinOrbit_V0_p": 9.858991085,
    "WLHRealSpinOrbit_V1_p": 0.0091306402,
    "WLHRealSpinOrbit_r0_p": 1.3080430737,
    "WLHRealSpinOrbit_r1_p": 0.929617936,
    "WLHRealSpinOrbit_a0_p": 0.8371062801,
    "WLHRealSpinOrbit_a1_p": 0.0003315958,
    "WLHRealSpinOrbit_V0_n": 9.2297197678,
    "WLHRealSpinOrbit_V1_n": 0.0091814506,
    "WLHRealSpinOrbit_r0_n": 1.3747431558,
    "WLHRealSpinOrbit_r1_n": 1.0335260482,
    "WLHRealSpinOrbit_a0_n": 0.8865305662,
    "WLHRealSpinOrbit_a1_n": 0.000324657
  }
]