{
  "WLHReal_V0_p": 54.2636158403,
  "WLHReal_V1_p": 0.3065988348,
  "WLHReal_V2_p": 3.73114e-05,
  "WLHReal_V3_p": 2.0355e-06,
  "WLHReal_V4_p": 13.185127209,
  "WLHReal_V5_p": 0.1282909778,
  "WLHReal_V6_p": 0.0002720317,
  "WLHReal_r0_p": 1.2857836762,
  "WLHReal_r1_p": 0.2747824391,
  "WLHReal_r2_p": 0.0008094149,
  "WLHReal_r3_p": 6.5604e-06,
  "WLHReal_a0_p": 0.773404891,
  "WLHReal_a1_p": 0.0001157213,
  "WLHReal_a2_p": 4.7646e-06,
  "WLHReal_a3_p": 0.0605428634,
  "WLHReal_a4_p": 0.5763632462,
  "WLHReal_V0_n": 54.6365736474,
  "WLHReal_V1_n": 0.2981842485,
  "WLHReal_V2_n": 0.0003402085,
  "WLHReal_V3_n": -3.8e-09,
  "WLHReal_V4_n": 21.8130885854,
  "WLHReal_V5_n": 0.2417849423,
  "WLHReal_V6_n": 0.0005612131,
  "WLHReal_r0_n": 1.240901856,
  "WLHReal_r1_n": 0.2695536907,
  "WLHReal_r2_n": 0.0005887549,
  "WLHReal_r3_n": 3.8454e-06,
  "WLHReal_a0_n": 0.7130095456,
  "WLHReal_a1_n": 0.0004031358,
  "WLHReal_a2_n": 2.9305e-06,
  "WLHReal_a3_n": 0.2488091452,
  "WLHReal_a4_n": 0.7567779,
  "WLHImagVolume_W0_p": 4.0989454011,
  "WLHImagVolume_W1_p": 0.2261211783,
  "WLHImagVolume_W2_p": 0.0003467517,
  "WLHImagVolume_W3_p": 12.0446259367,
  "WLHImagVolume_W4_p": 0.0731945435,
  "WLHImagVolume_r0_p": 0.63792333,
  "WLHImagVolume_r1_p": 48.8158306261,
  "WLHImagVolume_r2_p": 0.6102217201,
  "WLHImagVolume_r3_p": 61.1978097858,
  "WLHImagVolume_r4_p": 0.65088069,
  "WLHImagVolume_r5_p": 1.8289e-06,
  "WLHImagVolume_a0_p": 0.5468167017,
  "WLHImagVolume_a1_p": 0.2763175492,
  "WLHImagVolume_a2_p": 14.7198672325,
  "WLHImagVolume_a3_p": 0.4060712549,
  "WLHImagVolume_a4_p": 0.002212993,
  "WLHImagVolume_W0_n": 2.264910197,
  "WLHImagVolume_W1_n": 0.2157614475,
  "WLHImagVolume_W2_n": 0.0003003768,
  "WLHImagVolume_W3_n": 7.98429756,
  "WLHImagVolume_W4_n": 0.0360293399,
  "WLHImagVolume_r0_n": 0.5625179064,
  "WLHImagVolume_r1_n": 71.2012168075,
  "WLHImagVolume_r2_n": 0.672410267,
  "WLHImagVolume_r3_n": 71.6280348728,
  "WLHImagVolume_r4_n": 0.9090404861,
  "WLHImagVolume_r5_n": 2.2557e-06,
  "WLHImagVolume_a0_n": 0.1864155301,
  "WLHImagVolume_a1_n": 0.6156139923,
  "WLHImagVolume_a2_n": 9.0546545803,
  "WLHImagVolume_a3_n": 0.0522121911,
  "WLHImagVolume_a4_n": 0.0005826993,
  "WLHImagSurface_W0_p": 0.938786299,
  "WLHImagSurface_W1_p": 0.03533839,
  "WLHImagSurface_W2_p": 0.7598911406,
  "WLHImagSurface_W3_p": 0.1177823206,
  "WLHImagSurface_r0_p": 0.9902165827,
  "WLHImagSurface_r1_p": 0.5232976262,
  "WLHImagSurface_r2_p": 0.0048182263,
  "WLHImagSurface_a0_p": 0.7885500081,
  "WLHImagSurface_W0_n": 1.6029502588,
  "WLHImagSurface_W1_n": 0.0224821282,
  "WLHImagSurface_W2_n": 1.9528786896,
  "WLHImagSurface_W3_n": 0.0788893035,
  "WLHImagSurface_r0_n": 1.2684036684,
  "WLHImagSurface_r1_n": 1.3095163446,
  "WLHImagSurface_r2_n": 0.0041174222,
  "WLHImagSurface_a0_n": 0.8227810029,
  "WLHRealSpinOrbit_V0_p": 9.7463830476,
  "WLHRealSpinOrbit_V1_p": 0.0084871684,
  "WLHRealSpinOrbit_r0_p": 1.2590664276,
  "WLHRealSpinOrbit_r1_p": 0.846029268,
  "WLHRealSpinOrbit_a0_p": 0.7916450365,
  "WLHRealSpinOrbit_a1_p": 0.0003459885,
  "WLHRealSpinOrbit_V0_n": 10.0291299015,
  "WLHRealSpinOrbit_V1_n": 0.0083912661,
  "WLHRealSpinOrbit_r0_n": 1.22172103,
  "WLHRealSpinOrbit_r1_n": 0.7879943439,
  "WLHRealSpinOrbit_a0_n": 0.7632696085,
  "WLHRealSpinOrbit_a1_n": 0.0003499496
}