{
  "WLHReal_V0_p": 54.1948657334,
  "WLHReal_V1_p": 0.3325938307,
  "WLHReal_V2_p": -0.0008325104,
  "WLHReal_V3_p": 5.4124e-06,
  "WLHReal_V4_p": 9.4933448551,
  "WLHReal_V5_p": 0.1533660079,
  "WLHReal_V6_p": 0.000616021,
  "WLHReal_r0_p": 1.3829995461,
  "WLHReal_r1_p": 0.3601964147,
  "WLHReal_r2_p": 0.0012111278,
  "WLHReal_r3_p": 1.16807e-05,
  "WLHReal_a0_p": 0.832492121,
  "WLHReal_a1_p": 0.000205055,
  "WLHReal_a2_p": 1.07662e-05,
  "WLHReal_a3_p": 0.030725273,
  "WLHReal_a4_p": 0.6626267459,
  "WLHReal_V0_n": 57.3606102502,
  "WLHReal_V1_n": 0.319624553,
  "WLHReal_V2_n": 0.0005731393,
  "WLHReal_V3_n": -3.477e-07,
  "WLHReal_V4_n": 21.3306864143,
  "WLHReal_V5_n": 0.2414528171,
  "WLHReal_V6_n": 0.0003368484,
  "WLHReal_r0_n": 1.2457235789,
  "WLHReal_r1_n": 0.3716687213,
  "WLHReal_r2_n": 0.0003314682,
  "WLHReal_r3_n": -1.635e-06,
  "WLHReal_a0_n": 0.70387391,
  "WLHReal_a1_n": 1.51094e-05,
  "WLHReal_a2_n": -3.9449e-06,
  "WLHReal_a3_n": 0.1394845267,
  "WLHReal_a4_n": 0.5436548678,
  "WLHImagVolume_W0_p": 6.7759883422,
  "WLHImagVolume_W1_p": 0.3437090712,
  "WLHImagVolume_W2_p": 0.0007512273,
  "WLHImagVolume_W3_p": 13.5426030709,
  "WLHImagVolume_W4_p": 0.1181619638,
  "WLHImagVolume_r0_p": 0.6061982385,
  "WLHImagVolume_r1_p": 56.6518628364,
  "WLHImagVolume_r2_p": 0.7350411953,
  "WLHImagVolume_r3_p": 68.5577621326,
  "WLHImagVolume_r4_p": 0.5643782915,
  "WLHImagVolume_r5_p": 1.0209e-06,
  "WLHImagVolume_a0_p": 0.6392133934,
  "WLHImagVolume_a1_p": 0.2662986314,
  "WLHImagVolume_a2_p": 14.7226326339,
  "WLHImagVolume_a3_p": 0.4924959048,
  "WLHImagVolume_a4_p": 0.0036516333,
  "WLHImagVolume_W0_n": 2.3191448332,
  "WLHImagVolume_W1_n": 0.2832904718,
  "WLHImagVolume_W2_n": 0.0005132396,
  "WLHImagVolume_W3_n": 8.3754118381,
  "WLHImagVolume_W4_n": 0.0762366607,
  "WLHImagVolume_r0_n": 0.5061249905,
  "WLHImagVolume_r1_n": 69.6840448162,
  "WLHImagVolume_r2_n": 0.7290219131,
  "WLHImagVolume_r3_n": 69.5537116738,
  "WLHImagVolume_r4_n": 0.9024229399,
  "WLHImagVolume_r5_n": 1.9904e-06,
  "WLHImagVolume_a0_n": 0.1848719448,
  "WLHImagVolume_a1_n": 0.6358002835,
  "WLHImagVolume_a2_n": 8.6915583554,
  "WLHImagVolume_a3_n": 0.0478943377,
  "WLHImagVolume_a4_n": 0.0008632845,
  "WLHImagSurface_W0_p": 0.551314857,
  "WLHImagSurface_W1_p": 0.0199181884,
  "WLHImagSurface_W2_p": -0.0775355221,
  "WLHImagSurface_W3_p": 0.0805653688,
  "WLHImagSurface_r0_p": 0.8147805688,
  "WLHImagSurface_r1_p": 0.2266236179,
  "WLHImagSurface_r2_p": -0.0013186446,
  "WLHImagSurface_a0_p": 0.7516325453,
  "WLHImagSurface_W0_n": 2.0300168014,
  "WLHImagSurface_W1_n": 0.0325091005,
  "WLHImagSurface_W2_n": 3.1267816305,
  "WLHImagSurface_W3_n": 0.1121543004,
  "WLHImagSurface_r0_n": 1.2686367637,
  "WLHImagSurface_r1_n": 1.3769694497,
  "WLHImagSurface_r2_n": 0.0047835744,
  "WLHImagSurface_a0_n": 0.807573689,
  "WLHRealSpinOrbit_V0_p": 9.0975543418,
  "WLHRealSpinOrbit_V1_p": 0.008785227,
  "WLHRealSpinOrbit_r0_p": 1.3433338927,
  "WLHRealSpinOrbit_r1_p": 0.9935305131,
  "WLHRealSpinOrbit_a0_p": 0.8607127088,
  "WLHRealSpinOrbit_a1_p": 0.0003086523,
  "WLHRealSpinOrbit_V0_n": 9.9476202562,
  "WLHRealSpinOrbit_V1_n": 0.0081515624,
  "WLHRealSpinOrbit_r0_n": 1.2079199243,
  "WLHRealSpinOrbit_r1_n": 0.7631509594,
  "WLHRealSpinOrbit_a0_n": 0.7487254175,
  "WLHRealSpinOrbit_a1_n": 0.0003515324
}